pyspeedboost/__init__.py
pyspeedboost/cli.py
pyspeedboost/compiler.py
pyspeedboost/config.py
pyspeedboost/exceptions.py
pyspeedboost/utils.py
pyspeedboost-0.2.0.dist-info/METADATA
pyspeedboost-0.2.0.dist-info/WHEEL
pyspeedboost-0.2.0.dist-info/entry_points.txt
pyspeedboost-0.2.0.dist-info/top_level.txt
pyspeedboost-0.2.0.dist-info/RECORD
